swcr2/__init__.py
swcr2/swcr2.py
swcr2/template.docx
swcr2-1.0.8.dist-info/LICENSE.txt
swcr2-1.0.8.dist-info/METADATA
swcr2-1.0.8.dist-info/WHEEL
swcr2-1.0.8.dist-info/entry_points.txt
swcr2-1.0.8.dist-info/top_level.txt
swcr2-1.0.8.dist-info/RECORD
