Metadata-Version: 2.1
Name: swcr2
Version: 1.0.8
Summary: 计算机软件著作权程序鉴别材料（即源代码）生成器
Home-page: https://github.com/kenley2021/swcr2
Author: kenley
Author-email: kenley2021@gmail.com
License: MIT
Platform: UNKNOWN
Classifier: License :: OSI Approved :: MIT License
Classifier: Programming Language :: Python
Classifier: Programming Language :: Python :: 3
Classifier: Programming Language :: Python :: 3.6
Classifier: Programming Language :: Python :: Implementation :: CPython
Classifier: Programming Language :: Python :: Implementation :: PyPy
Requires-Python: >=3.6.0
License-File: LICENSE.txt
Requires-Dist: click
Requires-Dist: scandir
Requires-Dist: python-docx
